cake.py
setup.py
cake_build.egg-info/PKG-INFO
cake_build.egg-info/SOURCES.txt
cake_build.egg-info/dependency_links.txt
cake_build.egg-info/entry_points.txt
cake_build.egg-info/top_level.txt