Metadata-Version: 1.0
Name: cake-build
Version: 0.0.1
Summary: metabuild for c/c++
Home-page: https://github.com/mylhne/cake
Author: Myles Hathcock
Author-email: myles@mylhne.sh
License: MIT
Platform: UNKNOWN
